MANIFEST.in
README.rst
setup.py
azure_helper/__init__.py
azure_helper/apim.py
azure_helper/azure_token.py
azure_helper/constants.py
azure_helper/environments.py
azure_helper/groups.py
azure_helper/helpers.py
azure_helper/products.py
azure_helper/subscriptions.py
azure_helper/users.py
azure_helper/web_api.py
azure_helper.egg-info/PKG-INFO
azure_helper.egg-info/SOURCES.txt
azure_helper.egg-info/dependency_links.txt
azure_helper.egg-info/not-zip-safe
azure_helper.egg-info/requires.txt
azure_helper.egg-info/top_level.txt